dpbench/__init__.py
dpbench/benchmark.py
dpbench/runner.py
dpbench/agents/__init__.py
dpbench/agents/philosopher.py
dpbench/config/__init__.py
dpbench/config/prompts.py
dpbench/core/__init__.py
dpbench/core/environment.py
dpbench/core/types.py
dpbench/evaluation/__init__.py
dpbench/evaluation/logger.py
dpbench/evaluation/metrics.py
dpbench/graph/__init__.py
dpbench/graph/builder.py
dpbench/graph/nodes.py
dpbench/graph/state.py
dpbench/models/__init__.py
dpbench/models/base.py
dpbench/ui/__init__.py
dpbench/ui/colors.py
dpbench/ui/components.py
dpbench/ui/console.py
dpbench-0.1.0.dist-info/LICENSE
dpbench-0.1.0.dist-info/METADATA
dpbench-0.1.0.dist-info/WHEEL
dpbench-0.1.0.dist-info/top_level.txt
dpbench-0.1.0.dist-info/RECORD
