Metadata-Version: 2.1
Name: dpbench
Version: 0.1.0
Summary: DPBench: A Benchmark for LLM Multi-Agent Coordination
Author: Najmul Hasan, Prashanth BusiReddyGari
License: MIT
Project-URL: Homepage, https://github.com/najmulhasan-code/dpbench
Project-URL: Repository, https://github.com/najmulhasan-code/dpbench
Keywords: llm,multi-agent,coordination,benchmark,dining-philosophers,deadlock
Classifier: Development Status :: 3 - Alpha
Classifier: Intended Audience :: Science/Research
Classifier: Programming Language :: Python :: 3
Classifier: Programming Language :: Python :: 3.10
Classifier: Programming Language :: Python :: 3.11
Classifier: Programming Language :: Python :: 3.12
Classifier: Topic :: Scientific/Engineering :: Artificial Intelligence
Requires-Python: >=3.10
License-File: LICENSE
Requires-Dist: langgraph>=0.2.0
Requires-Dist: numpy>=1.24.0
Requires-Dist: scipy>=1.10.0
Requires-Dist: python-dotenv>=1.0.0
Requires-Dist: pyyaml>=6.0.0
Provides-Extra: anthropic
Requires-Dist: anthropic>=0.21.0; extra == "anthropic"
Provides-Extra: dev
Requires-Dist: pytest>=7.0.0; extra == "dev"
Requires-Dist: black>=23.0.0; extra == "dev"
Requires-Dist: ruff>=0.1.0; extra == "dev"
Provides-Extra: google
Requires-Dist: google-genai>=1.0.0; extra == "google"
Provides-Extra: openai
Requires-Dist: openai>=1.0.0; extra == "openai"
Provides-Extra: xai
Requires-Dist: openai>=1.0.0; extra == "xai"
